{
  "filename": "Al jul volke JSB 2",
  "title": "AL JUL VOLKE KLAP JUL HANDE (JSB 2, NO. 3)",
  "artist": "",
  "lyrics": [
    "AL JUL VOLKE KLAP JUL HANDE (JSB 2, NO. 3)",
    "1. Al jul volke klap jul hande: juig tot eer van God.",
    "Verhef jul stem en roem sy Naam in elke stad op aarde!",
    "Refrein:",
    "Sing en sing en sing dan saam; loof en prys sy grote Naam,",
    "want Hy is ewig Koning in die hemel en op aarde!",
    "Sing en sing en sing dan saam; loof en prys sy grote Naam,",
    "want die Hemelkoning skenk ons sy ge-nade!",
    "2. Hy is Koning ewig in die hemel en op aarde!",
    "Die volke kniel, die nasies juig oor al sy skeppingsdade.",
    "3. Ons gaan in sy tempel in, Hy roep ons almal saam;",
    "die skare juig en horings blaas, ons almal roem sy Naam"
  ],
  "chords": [
    "Em Em B7 Em",
    "Em Em B7 Em",
    "G D",
    "C D7 G G D",
    "G D",
    "C D7 Em"
  ],
  "metadata": {},
  "raw_text": "AL JUL VOLKE KLAP JUL HANDE (JSB 2, NO. 3)\nEm Em B7 Em\n1. Al jul volke klap jul hande: juig tot eer van God.\nEm Em B7 Em\nVerhef jul stem en roem sy Naam in elke stad op aarde!\nRefrein:\nG D\nSing en sing en sing dan saam; loof en prys sy grote Naam,\nC D7 G G D\nwant Hy is ewig Koning in die hemel en op aarde!\nG D\nSing en sing en sing dan saam; loof en prys sy grote Naam,\nC D7 Em\nwant die Hemelkoning skenk ons sy ge-nade!\n2. Hy is Koning ewig in die hemel en op aarde!\nDie volke kniel, die nasies juig oor al sy skeppingsdade.\n3. Ons gaan in sy tempel in, Hy roep ons almal saam;\ndie skare juig en horings blaas, ons almal roem sy Naam"
}