{
  "filename": "Ek soek na die lewende water ML (Vonkk 18)",
  "title": "VONKK 18",
  "artist": "",
  "lyrics": [
    "VONKK 18",
    "Ek Soek Na Die Lewende Water",
    "(Psalm 42 en 43)",
    "q. = 52",
    "                          ",
    "  ",
    "1. Ek soek na die le-wen-de wa- ter, ek roep en dors na U, Heer— wantek",
    "2. Hul spot en hul vra my aan - hou dend: Waar is dié God van jou nou? Al het",
    "3. O He -re, kom red en ver-hoor my, help my enspreekmy tog vry — met",
    "4. Kom stuur nou u lig en u waar heid, laat dit my lei na u huis— want,",
    " ",
    "  ",
    "                 ",
    " ",
    "huil dag en nag, o He - re, ek smag om by U te wees nog 'n keer.",
    "gol - we van swaar - kry oor my ge-spoel, tog wéét ek ek kan U ver - trou.",
    "vals-heid wil bo - se men - se my vang, maar U is 'n skuil-plek vir my.",
    "God, U's my God, die bron van my lof, my lied sal U ju - be-lend prys.",
    "Refrein:",
    "  ",
    "                       ",
    " ",
    "Al is ek ont -steld en mis-moe-dig, met hart-seer en on -rus om -ring, weet ek",
    " ",
    "                ",
    "    ",
    "",
    "God is my hoop, Hy help my weer op— ek sal al my lof aan Hom bring.",
    "Psalm 42 en 43",
    "Teks : Driekie Jankowitz 2008 (Pro Deo)",
    "Melodie: AUAS - Jacus Krige 2008",
    "RUBRIEK: Kontemporêr - Toetrede en Aanroeping"
  ],
  "chords": [
    "E Amaj7 F#m7 B",
    "5 E E/D© A/C© E/B A F©7/A© B7",
    "9 E Amaj7 F#m7 Bsus4 B",
    "13 E E/G# A A/C© F#m B7 E"
  ],
  "metadata": {},
  "raw_text": "VONKK 18\nEk Soek Na Die Lewende Water\n(Psalm 42 en 43)\nq. = 52\nE Amaj7 F#m7 B\n                          \n  \n1. Ek soek na die le-wen-de wa- ter, ek roep en dors na U, Heer— wantek\n2. Hul spot en hul vra my aan - hou dend: Waar is dié God van jou nou? Al het\n3. O He -re, kom red en ver-hoor my, help my enspreekmy tog vry — met\n4. Kom stuur nou u lig en u waar heid, laat dit my lei na u huis— want,\n5 E E/D© A/C© E/B A F©7/A© B7\n \n  \n                 \n \nhuil dag en nag, o He - re, ek smag om by U te wees nog 'n keer.\ngol - we van swaar - kry oor my ge-spoel, tog wéét ek ek kan U ver - trou.\nvals-heid wil bo - se men - se my vang, maar U is 'n skuil-plek vir my.\nGod, U's my God, die bron van my lof, my lied sal U ju - be-lend prys.\nRefrein:\n9 E Amaj7 F#m7 Bsus4 B\n  \n                       \n \nAl is ek ont -steld en mis-moe-dig, met hart-seer en on -rus om -ring, weet ek\n13 E E/G# A A/C© F#m B7 E\n \n                \n    \n\nGod is my hoop, Hy help my weer op— ek sal al my lof aan Hom bring.\nPsalm 42 en 43\nTeks : Driekie Jankowitz 2008 (Pro Deo)\nMelodie: AUAS - Jacus Krige 2008\n© 2009 VONKK Uitgewers (admin Bybel-Media)\nRUBRIEK: Kontemporêr - Toetrede en Aanroeping"
}