{
  "filename": "Gee genadig broosheid, Heer ML (Vonkk 372) Be-genadig",
  "title": "VONKK 372",
  "artist": "",
  "lyrics": [
    "VONKK 372",
    "Gee genadig broosheid, Heer",
    "q = 100",
    "  ",
    "",
    "                   ",
    "1. Gee ge - na - dig broos-heid, Heer, dat ek van breek-baar - heid be - wus, my",
    "2. Gee my sag - te voe - te, Heer,wat sag- voets deur u wê-reld stap – nie",
    "3. Maak my ra - dar teer- heid, Heer, so - dat ek nooit met woord of daad my",
    "4. Maak, o God, my be - ne bros, so - dat ek slegs op U moet steun,dat",
    "5. Laat, Heer, deer-nis dien as krag, as sag - te skild in el - ke stryd, as",
    "",
    "               (       )",
    "drang na twis sal blus. O, gee my broos-heid,Heer.",
    "voor die voet ver- trap. Gee sag - te voe - te, Heer.",
    "me -de-mens be - seer. O, gee my teer -heid,Heer.",
    "ek u hand nooit los. Maak, Heer,my be - ne bros.",
    "vaan-del van u mag. Laat deer-nis dien as krag.",
    "Teks: Neels Jackson 2017 ©",
    "Melodie: LOTUSBLOM Anton Esterhuyse 2017 ©",
    "Orrelbegeleiding: Anton Esterhuyse 2017 ©",
    "Musikale verryking: Anton Esterhuyse 2017 ©",
    "RUBRIEK: Kontemporêr – Gebede / Liefde, Dankbaarheid en Diens / Missionaal"
  ],
  "chords": [
    "D A",
    "D A/D G E‹",
    "5 F©‹ B‹ C(“2) A‹ D(“4) D C(“2) A‹ D(“4) D"
  ],
  "metadata": {},
  "raw_text": "VONKK 372\nGee genadig broosheid, Heer\nq = 100\nD A\nD A/D G E‹\n  \n\n                   \n1. Gee ge - na - dig broos-heid, Heer, dat ek van breek-baar - heid be - wus, my\n2. Gee my sag - te voe - te, Heer,wat sag- voets deur u wê-reld stap – nie\n3. Maak my ra - dar teer- heid, Heer, so - dat ek nooit met woord of daad my\n4. Maak, o God, my be - ne bros, so - dat ek slegs op U moet steun,dat\n5. Laat, Heer, deer-nis dien as krag, as sag - te skild in el - ke stryd, as\n5 F©‹ B‹ C(“2) A‹ D(“4) D C(“2) A‹ D(“4) D\n\n               (       )\ndrang na twis sal blus. O, gee my broos-heid,Heer.\nvoor die voet ver- trap. Gee sag - te voe - te, Heer.\nme -de-mens be - seer. O, gee my teer -heid,Heer.\nek u hand nooit los. Maak, Heer,my be - ne bros.\nvaan-del van u mag. Laat deer-nis dien as krag.\nTeks: Neels Jackson 2017 ©\nMelodie: LOTUSBLOM Anton Esterhuyse 2017 ©\nOrrelbegeleiding: Anton Esterhuyse 2017 ©\nMusikale verryking: Anton Esterhuyse 2017 ©\n© 2017 VONKK-Uitgewers (admin Bybel-Media)\nRUBRIEK: Kontemporêr – Gebede / Liefde, Dankbaarheid en Diens / Missionaal"
}