{
  "filename": "Gekruisigde hande",
  "title": "Gekruisigde hande",
  "artist": "",
  "lyrics": [
    "Gekruisigde hande",
    "Louis Brittz",
    "Vers 1",
    "Die lewe by ons is nogal soet",
    "Maar die wiele draai vir die kinders van Beiroet",
    "2 7",
    "Die vroue in Kairo is moeg gewag vir later",
    "2 7",
    "Die Koerde in Turkye vra waar’s die lewenswater",
    "#",
    "Kan iemand hoor hoe hulle roep",
    "Refrein:",
    "Here, gee my, gekruisigde hande wat gee",
    "Gekruisigde voete wat loop, waar Hy sou loop.",
    "2",
    "Van myself gestroop",
    "‘n hart waarin waarheid kan groei",
    "En trane wat vryelik vloei",
    "7",
    "As wor – tel – diep sy liefde groei",
    "Vers 2",
    "Die nuus op die TV laat my sug",
    "Ek raak dit al gewoond en ek draai my rug",
    "2 7",
    "Maar ‘n bedelaar in Indië se oë is verwytend",
    "2 7",
    "En deur sy harde masker sien ek sy oë is pleitend",
    "En Jesus vra waarom ek vlug",
    "Refrein:",
    "Here, gee my, gekruisigde hande wat gee",
    "Gekruisigde voete wat loop, waar Hy sou loop.",
    "Van myself gestroop",
    "‘n hart waarin waarheid kan groei",
    "En trane wat vryelik vloei",
    "7",
    "As wor – tel – diep sy liefde groei",
    "Brug:",
    "Ek weet dat iemand sal moet gaan dat ander kan verstaan",
    "Ek weet dat iemand sal moet sterf dat ander Hom kan erf."
  ],
  "chords": [
    "C F G",
    "C F G",
    "F C /E Dm G C",
    "F C /E Dm G C",
    "F D/F Gsus G",
    "C F G",
    "C F G Am G F",
    "C",
    "/E Gsus G",
    "C F G",
    "C F G",
    "Am G F Dm Gsus G",
    "C F G",
    "C F G",
    "F C /E Dm G C",
    "F C /E Dm G C",
    "F D/F# Gsus G",
    "C F G",
    "C F G Am G F",
    "C2/E Gsus G",
    "C F G",
    "C F G",
    "Am G F Dm Gsus G",
    "F G C F C Gsus",
    "F G C G/B Am Dm Gsus"
  ],
  "metadata": {},
  "raw_text": "Gekruisigde hande\nLouis Brittz\nVers 1\nC F G\nDie lewe by ons is nogal soet\nC F G\nMaar die wiele draai vir die kinders van Beiroet\n2 7\nF C /E Dm G C\nDie vroue in Kairo is moeg gewag vir later\n2 7\nF C /E Dm G C\nDie Koerde in Turkye vra waar’s die lewenswater\n#\nF D/F Gsus G\nKan iemand hoor hoe hulle roep\nRefrein:\nC F G\nHere, gee my, gekruisigde hande wat gee\nC F G Am G F\nGekruisigde voete wat loop, waar Hy sou loop.\nC\n2\n/E Gsus G\nVan myself gestroop\nC F G\n‘n hart waarin waarheid kan groei\nC F G\nEn trane wat vryelik vloei\n7\nAm G F Dm Gsus G\nAs wor – tel – diep sy liefde groei\nVers 2\nC F G\nDie nuus op die TV laat my sug\nC F G\nEk raak dit al gewoond en ek draai my rug\n2 7\nF C /E Dm G C\nMaar ‘n bedelaar in Indië se oë is verwytend\n2 7\nF C /E Dm G C\nEn deur sy harde masker sien ek sy oë is pleitend\nF D/F# Gsus G\nEn Jesus vra waarom ek vlug\nRefrein:\nC F G\nHere, gee my, gekruisigde hande wat gee\nC F G Am G F\nGekruisigde voete wat loop, waar Hy sou loop.\nC2/E Gsus G\nVan myself gestroop\nC F G\n‘n hart waarin waarheid kan groei\nC F G\nEn trane wat vryelik vloei\n7\nAm G F Dm Gsus G\nAs wor – tel – diep sy liefde groei\nBrug:\nF G C F C Gsus\nEk weet dat iemand sal moet gaan dat ander kan verstaan\nF G C G/B Am Dm Gsus\nEk weet dat iemand sal moet sterf dat ander Hom kan erf."
}