{
  "filename": "Heer, ons dink aan Afrika KV (Vonkk 159)",
  "title": "VONKK 159",
  "artist": "",
  "lyrics": [
    "VONKK 159",
    "Heer, Ons Dink Aan Afrika",
    "(Plea from Africa)",
    "q = 86 Kantoryverwerking",
    "",
    "Koor             ",
    "1.Heer,ons",
    "Eenstemmig:",
    "2.Heer,ons",
    "                                                        ",
    "Klavier",
    "",
    "                       ",
    "  ",
    "6",
    "",
    "                              ",
    "                                          ",
    "",
    "         ",
    "      ",
    "    ",
    "",
    "12",
    "",
    " ",
    "       –            ",
    " ",
    "wag op God se Woord– men-se smag-tend in hul nood na die God van",
    "om tot U te keer. Laat u ko - nin-kryk hier kom en u wil ge -",
    "3",
    "                                      ",
    "",
    " ",
    "             ",
    "  ",
    "17",
    "",
    " ",
    "             ",
    "  ",
    "hoop. Hoor ons smeek - ge-bed, o Heer, Va - der wat re -",
    "",
    "",
    "                      ",
    "        ",
    "  ",
    "    ",
    "2",
    "21 Refrein: Bring die lief - de van ons Heer na die men - se wat hier",
    "  ",
    "  ",
    "geer.",
    "lief-de van ons Heer men-se wat hier",
    "vra.",
    "   ",
    "T      ",
    "",
    "",
    " ",
    "       ",
    "                                   ",
    "",
    "  ",
    "     ",
    "                        ",
    "25",
    " ",
    "                                ",
    "",
    " ",
    "                                     ",
    "  ",
    "",
    "                                 ",
    "  ",
    "                     ",
    "           ",
    " ",
    "1. 2.",
    "Give a thought to Africa 'neath the burning sun. Breath a prayer for Africa. God, the father's love",
    "There are hosts of weary hearts waiting to be won. can reach down and bless all hearts, from His heav'n above.",
    "Many lives have passed away; and in many homes And when lips are moved by grace, they so sweetly sing;",
    "there are voices crying now to the living God. Pray for peace in Africa from our living God",
    "Refrain:",
    "Tell the love of Jesus by her hills and waters.",
    "God bless Africa and her sons and daugters.",
    "Melodie: PLEA FROM AFRICA – John Knox Bokwe (1855-1922)",
    "Orrelbegeleiding: VONKK Werkgroep 2011",
    "Klavierbegeleiding: Tradisioneel",
    "Kantoryverwerking: Onbekend",
    "Musikale verryking: Anton Esterhuyse 2009",
    "2011 VONKK Uitgewers (admin Bybel-Media)",
    "RUBRIEK: Tradisioneel – Gebed / Barmhartigheid en Getuienis"
  ],
  "chords": [
    "dink aan A- fri - ka, land van hel -der son. So-veel men -se wat hier woon,",
    "bid vir A- fri - ka, waar U ook re- ge.er. Raak die har - de har -te aan",
    "skied. Hoor ons pleit vir A - fri - ka, Va - der, as ons",
    "S A                                        ",
    "B                       ",
    "woon. Seën A - fri - ka! Laat onssaam in vre - de woon.",
    "Teks: Give a thought to Africa – A Glasgow Lady; Afrikaanse weergawe: Jacques Louw 2011 ©"
  ],
  "metadata": {},
  "raw_text": "VONKK 159\nHeer, Ons Dink Aan Afrika\n(Plea from Africa)\nq = 86 Kantoryverwerking\n\nKoor             \n1.Heer,ons\nEenstemmig:\n2.Heer,ons\n                                                        \nKlavier\n\n                       \n  \n6\n\n                              \ndink aan A- fri - ka, land van hel -der son. So-veel men -se wat hier woon,\nbid vir A- fri - ka, waar U ook re- ge.er. Raak die har - de har -te aan\n                                          \n\n         \n      \n    \n\n12\n\n \n       –            \n \nwag op God se Woord– men-se smag-tend in hul nood na die God van\nom tot U te keer. Laat u ko - nin-kryk hier kom en u wil ge -\n3\n                                      \n\n \n             \n  \n17\n\n \n             \n  \nhoop. Hoor ons smeek - ge-bed, o Heer, Va - der wat re -\nskied. Hoor ons pleit vir A - fri - ka, Va - der, as ons\n\n\n                      \n        \n  \n    \n2\n21 Refrein: Bring die lief - de van ons Heer na die men - se wat hier\n  \nS A                                        \n  \ngeer.\nlief-de van ons Heer men-se wat hier\nvra.\n   \nT      \nB                       \n\n\n \n       \n                                   \n\n  \n     \n                        \n25\n \n                                \n\nwoon. Seën A - fri - ka! Laat onssaam in vre - de woon.\n \n                                     \n  \n\n                                 \n  \n                     \n           \n \n1. 2.\nGive a thought to Africa 'neath the burning sun. Breath a prayer for Africa. God, the father's love\nThere are hosts of weary hearts waiting to be won. can reach down and bless all hearts, from His heav'n above.\nMany lives have passed away; and in many homes And when lips are moved by grace, they so sweetly sing;\nthere are voices crying now to the living God. Pray for peace in Africa from our living God\nRefrain:\nTell the love of Jesus by her hills and waters.\nGod bless Africa and her sons and daugters.\nTeks: Give a thought to Africa – A Glasgow Lady; Afrikaanse weergawe: Jacques Louw 2011 ©\nMelodie: PLEA FROM AFRICA – John Knox Bokwe (1855-1922)\nOrrelbegeleiding: VONKK Werkgroep 2011\nKlavierbegeleiding: Tradisioneel\nKantoryverwerking: Onbekend\nMusikale verryking: Anton Esterhuyse 2009\n© Afrikaanse teks, orrelbegeleiding en musikale verryking:\n2011 VONKK Uitgewers (admin Bybel-Media)\n© Engelse teks, melodie en klavierbegeleiding: Openbare besit\nRUBRIEK: Tradisioneel – Gebed / Barmhartigheid en Getuienis"
}