{
  "filename": "Here, ons Here, hoe groot is U! OB (Vonkk 85)",
  "title": "VONKK 85",
  "artist": "",
  "lyrics": [
    "VONKK 85",
    "Here, Ons Here, Hoe Groot Is U!",
    "(Psalm 8)",
    "q = 74 Rustig, met eerbied",
    "Orrelbegeleiding",
    "Keervers:",
    "   Fine",
    "        ",
    "                               ",
    "He-re, ons He-re, hoegroot is U! He-re, ons He-re, hoegroot is U!",
    "",
    "                         ",
    "5 Strofes:",
    "    ",
    "",
    "                 ",
    "     ",
    "1. Kyk die he - mel en die aar - de wys die won-ders van u Naam. Kyk,die",
    "2. Al die kin- ders, selfs die klein-stes, wil oor U kom sing en juig. Al die",
    "3. Ons as men - se is maar nie - tig, tog gee U ons roem en eer. U ver-",
    "4. Al die die - re van die aar - de het U aan ons toe - ver- trou. U laat",
    "                ",
    "8",
    "     ",
    " ",
    "                  ",
    "maan - lig in die aan - de en die ster - re sê dit saam:",
    "men - se wat teen U is, sal ook voor U moet kom buig.",
    "sorg ons en U kroon ons om U skep - ping te re - geer.",
    "heers ons oor die skep - ping wat U in u han - de hou.",
    "            ",
    "",
    "Psalm 8",
    "Teks: Driekie Jankowitz 2010 (Pro Deo)",
    "Melodie: HENTIESBAAI – Driekie Jankowitz 2010 (Pro Deo)",
    "Orrelbegeleiding: Albert Troskie 2010 (Pro Deo)",
    "Kantoryverwerking: Albert Troskie 2010 (Pro Deo)",
    "Musikale verryking: Gerrit Jordaan 2011",
    "RUBRIEK: Kontemporêr - Verwondering"
  ],
  "chords": [
    "D.C. al fine"
  ],
  "metadata": {},
  "raw_text": "VONKK 85\nHere, Ons Here, Hoe Groot Is U!\n(Psalm 8)\nq = 74 Rustig, met eerbied\nOrrelbegeleiding\nKeervers:\n   Fine\n        \n                               \nHe-re, ons He-re, hoegroot is U! He-re, ons He-re, hoegroot is U!\n\n                         \n5 Strofes:\n    \n\n                 \n     \n1. Kyk die he - mel en die aar - de wys die won-ders van u Naam. Kyk,die\n2. Al die kin- ders, selfs die klein-stes, wil oor U kom sing en juig. Al die\n3. Ons as men - se is maar nie - tig, tog gee U ons roem en eer. U ver-\n4. Al die die - re van die aar - de het U aan ons toe - ver- trou. U laat\n                \n8\nD.C. al fine\n     \n \n                  \nmaan - lig in die aan - de en die ster - re sê dit saam:\nmen - se wat teen U is, sal ook voor U moet kom buig.\nsorg ons en U kroon ons om U skep - ping te re - geer.\nheers ons oor die skep - ping wat U in u han - de hou.\n            \n\nPsalm 8\nTeks: Driekie Jankowitz 2010 (Pro Deo)\nMelodie: HENTIESBAAI – Driekie Jankowitz 2010 (Pro Deo)\nOrrelbegeleiding: Albert Troskie 2010 (Pro Deo)\nKantoryverwerking: Albert Troskie 2010 (Pro Deo)\nMusikale verryking: Gerrit Jordaan 2011\n© 2010 VONKK Uitgewers (admin Bybel-Media)\nRUBRIEK: Kontemporêr - Verwondering"
}