{
  "filename": "Soos 'n flits in die donker ML (Vonkk 137)",
  "title": "VONKK 137",
  "artist": "",
  "lyrics": [
    "VONKK 137",
    "Soos 'n flits in die donker",
    "q = 116",
    "",
    "",
    "                      ",
    "Soos'n flits in die don-ker is die By-bel vir my; dis 'n lig wat my wys hoe ek",
    "",
    "                 ",
    "na -by God kan bly. Ek is lief vir U Heer, ek wil hoor wat U",
    "",
    "",
    "               ",
    "sê, want U woor-de leer vir my om te doen wat U wil hê.",
    "Nav Psalm 119: 97, 105",
    "Teks: Driekie Jankowitz 2010 (Pro Deo)",
    "Melodie: ANUSKA – Driekie Jankowitz 2010 (Pro Deo)",
    "Orrelbegeleiding: Daleen Kruger 2010 (Pro Deo)",
    "RUBRIEK: Kinderpsalm – Die Wil van God / Voorbereiding om God se Woord te hoor /",
    "Geloof en Vertroue / Kindwees"
  ],
  "chords": [
    "D A7 A/C© D B‹ E‹",
    "7 A D D G A7",
    "12 D B‹ E‹ A7 D"
  ],
  "metadata": {},
  "raw_text": "VONKK 137\nSoos 'n flits in die donker\nq = 116\nD A7 A/C© D B‹ E‹\n\n\n                      \nSoos'n flits in die don-ker is die By-bel vir my; dis 'n lig wat my wys hoe ek\n7 A D D G A7\n\n                 \nna -by God kan bly. Ek is lief vir U Heer, ek wil hoor wat U\n12 D B‹ E‹ A7 D\n\n\n               \nsê, want U woor-de leer vir my om te doen wat U wil hê.\nNav Psalm 119: 97, 105\nTeks: Driekie Jankowitz 2010 (Pro Deo)\nMelodie: ANUSKA – Driekie Jankowitz 2010 (Pro Deo)\nOrrelbegeleiding: Daleen Kruger 2010 (Pro Deo)\n© 2010 VONKK-Uitgewers (admin Bybel-Media)\nRUBRIEK: Kinderpsalm – Die Wil van God / Voorbereiding om God se Woord te hoor /\nGeloof en Vertroue / Kindwees"
}